cursorflow/__init__.py
cursorflow/auto_init.py
cursorflow/auto_updater.py
cursorflow/cli.py
cursorflow/install_cursorflow_rules.py
cursorflow/post_install.py
cursorflow/updater.py
cursorflow/core/action_validator.py
cursorflow/core/agent.py
cursorflow/core/auth_handler.py
cursorflow/core/browser_controller.py
cursorflow/core/browser_engine.py
cursorflow/core/config_validator.py
cursorflow/core/css_iterator.py
cursorflow/core/cursor_integration.py
cursorflow/core/cursorflow.py
cursorflow/core/data_presenter.py
cursorflow/core/error_context_collector.py
cursorflow/core/error_correlator.py
cursorflow/core/event_correlator.py
cursorflow/core/file_change_monitor.py
cursorflow/core/hmr_detector.py
cursorflow/core/json_utils.py
cursorflow/core/log_collector.py
cursorflow/core/log_monitor.py
cursorflow/core/mockup_comparator.py
cursorflow/core/output_manager.py
cursorflow/core/persistent_session.py
cursorflow/core/query_engine.py
cursorflow/core/report_generator.py
cursorflow/core/trace_manager.py
cursorflow/log_sources/local_file.py
cursorflow/log_sources/ssh_remote.py
cursorflow/rules/__init__.py
cursorflow/rules/cursorflow-installation.mdc
cursorflow/rules/cursorflow-usage.mdc
cursorflow-2.8.7.dist-info/licenses/LICENSE
cursorflow-2.8.7.dist-info/METADATA
cursorflow-2.8.7.dist-info/WHEEL
cursorflow-2.8.7.dist-info/entry_points.txt
cursorflow-2.8.7.dist-info/top_level.txt
cursorflow-2.8.7.dist-info/RECORD
