Metadata-Version: 2.4
Name: cursorflow
Version: 2.8.7
Summary: 🔥 Complete page intelligence for AI-driven development with Hot Reload Intelligence - captures DOM, network, console, performance, HMR events, and comprehensive page analysis
Author-email: GeekWarrior Development <rbush@cooltheory.com>
License-Expression: MIT
Project-URL: Homepage, https://github.com/haley-marketing-group/cursorflow
Project-URL: Documentation, https://cursorflow.dev
Project-URL: Repository, https://github.com/haley-marketing-group/cursorflow
Keywords: ui-testing,automation,cursor,ai,web-testing,css-iteration,hot-reload,hmr,element-intelligence,page-analysis,error-context
Classifier: Development Status :: 5 - Production/Stable
Classifier: Intended Audience :: Developers
Classifier: Programming Language :: Python :: 3
Classifier: Programming Language :: Python :: 3.8
Classifier: Programming Language :: Python :: 3.9
Classifier: Programming Language :: Python :: 3.10
Classifier: Programming Language :: Python :: 3.11
Classifier: Programming Language :: Python :: 3.12
Classifier: Topic :: Software Development :: Testing
Classifier: Topic :: Software Development :: Quality Assurance
Classifier: Framework :: AsyncIO
Requires-Python: >=3.8
License-File: LICENSE
Requires-Dist: playwright>=1.40.0
Requires-Dist: paramiko>=3.3.1
Requires-Dist: pyyaml>=6.0.1
Requires-Dist: asyncio-mqtt>=0.11.1
Requires-Dist: click>=8.1.7
Requires-Dist: rich>=13.6.0
Requires-Dist: jinja2>=3.1.2
Requires-Dist: python-dateutil>=2.8.2
Requires-Dist: watchdog>=3.0.0
Requires-Dist: docker>=6.1.3
Requires-Dist: pillow>=10.0.0
Requires-Dist: numpy>=1.24.0
Requires-Dist: websockets>=11.0.0
Provides-Extra: dev
Requires-Dist: pytest>=7.4.0; extra == "dev"
Requires-Dist: pytest-asyncio>=0.21.1; extra == "dev"
Requires-Dist: black>=23.9.1; extra == "dev"
Requires-Dist: flake8>=6.1.0; extra == "dev"
Requires-Dist: mypy>=1.6.1; extra == "dev"
Dynamic: license-file
